{
	"configurations" : 
	[
		{
			"directories" : 
			[
				{
					"build" : ".",
					"hasInstallRule" : true,
					"jsonFile" : "directory-.-c79ad422bf60585bd076.json",
					"minimumCMakeVersion" : 
					{
						"string" : "3.12"
					},
					"projectIndex" : 0,
					"source" : ".",
					"targetIndexes" : 
					[
						0,
						1
					]
				}
			],
			"name" : "",
			"projects" : 
			[
				{
					"directoryIndexes" : 
					[
						0
					],
					"name" : "golf_cart_description",
					"targetIndexes" : 
					[
						0,
						1
					]
				}
			],
			"targets" : 
			[
				{
					"directoryIndex" : 0,
					"id" : "golf_cart_description_uninstall::@6890427a1f51a3e7e1df",
					"jsonFile" : "target-golf_cart_description_uninstall-d163a0298fd3011fee66.json",
					"name" : "golf_cart_description_uninstall",
					"projectIndex" : 0
				},
				{
					"directoryIndex" : 0,
					"id" : "uninstall::@6890427a1f51a3e7e1df",
					"jsonFile" : "target-uninstall-96eedc6cc227a726174c.json",
					"name" : "uninstall",
					"projectIndex" : 0
				}
			]
		}
	],
	"kind" : "codemodel",
	"paths" : 
	{
		"build" : "/home/developer/ros2_ws/build/golf_cart_description",
		"source" : "/home/developer/ros2_ws/src/golf_cart_description"
	},
	"version" : 
	{
		"major" : 2,
		"minor" : 3
	}
}
